[
  [
    {
      "name": "长野"
    },
    {
      "name": "东京",
      "value": 300
    }
  ],
  [
    {
      "name": "名古屋"
    },
    {
      "name": "东京",
      "value": 300
    }
  ],
  [
    {
      "name": "大阪"
    },
    {
      "name": "东京",
      "value": 300
    }
  ],
  [
    {
      "name": "广岛"
    },
    {
      "name": "东京",
      "value": 160
    }
  ],
  [
    {
      "name": "京都"
    },
    {
      "name": "东京",
      "value": 20
    }
  ],
  [
    {
      "name": "福岛"
    },
    {
      "name": "东京",
      "value": 20
    }
  ],
  [
    {
      "name": "北海道"
    },
    {
      "name": "东京",
      "value": 10
    }
  ]
]